langgroup/__init__.py
langgroup/agent_system.py
langgroup/models.py
langgroup/py.typed
langgroup/team_supervisor.py
langgroup/agents/__init__.py
langgroup/agents/base_agent.py
langgroup/agents/supervisor_agent.py
langgroup-0.2.4.dist-info/licenses/LICENSE
langgroup-0.2.4.dist-info/METADATA
langgroup-0.2.4.dist-info/WHEEL
langgroup-0.2.4.dist-info/top_level.txt
langgroup-0.2.4.dist-info/RECORD
