Metadata-Version: 2.4
Name: langgroup
Version: 0.2.4
Summary: A multiagent system framework built on LangChain and LangGraph with supervisor-based coordination
Author-email: William Kang <willysk73@outlook.com>
License: MIT
Project-URL: Homepage, https://github.com/willysk73/langgroup
Project-URL: Documentation, https://github.com/willysk73/langgroup#readme
Project-URL: Repository, https://github.com/willysk73/langgroup
Project-URL: Bug Tracker, https://github.com/willysk73/langgroup/issues
Keywords: langchain,langgraph,multiagent,ai,agents,llm
Classifier: Development Status :: 3 - Alpha
Classifier: Intended Audience :: Developers
Classifier: License :: OSI Approved :: MIT License
Classifier: Programming Language :: Python :: 3
Classifier: Programming Language :: Python :: 3.10
Classifier: Programming Language :: Python :: 3.11
Classifier: Programming Language :: Python :: 3.12
Requires-Python: >=3.10
License-File: LICENSE
Requires-Dist: langchain>=0.1.0
Requires-Dist: langchain-openai>=0.0.5
Requires-Dist: langgraph>=0.0.20
Requires-Dist: python-dotenv>=1.0.0
Provides-Extra: dev
Requires-Dist: pytest>=8.0.0; extra == "dev"
Requires-Dist: black>=24.0.0; extra == "dev"
Requires-Dist: ruff>=0.1.0; extra == "dev"
Dynamic: license-file
